sb_orm_lite/__init__.py
sb_orm_lite/builder.py
sb_orm_lite/entity.py
sb_orm_lite/mapped_field.py
sb_orm_lite/mongorepository.py
sb_orm_lite/provider.py
sb_orm_lite/repository.py
sb_orm_lite-0.0.4.dist-info/LICENSE
sb_orm_lite-0.0.4.dist-info/METADATA
sb_orm_lite-0.0.4.dist-info/WHEEL
sb_orm_lite-0.0.4.dist-info/top_level.txt
sb_orm_lite-0.0.4.dist-info/RECORD
