Metadata-Version: 2.1
Name: sb-orm-lite
Version: 0.0.4
Summary: A lightweight orm implementation
Author-email: Stephen Booth <stephen.booth.za@gmail.com>
Classifier: Programming Language :: Python :: 3
Classifier: License :: OSI Approved :: MIT License
Classifier: Operating System :: OS Independent
Requires-Python: >=3.11
License-File: LICENSE
Requires-Dist: sb-db-common>=0.0.1
Requires-Dist: mysql-connector-python~=8.1.0
Requires-Dist: psycopg2~=2.9.9
Requires-Dist: pymongo~=4.10.1
Requires-Dist: sb-serializer~=0.0.3
